mgkegg/__init__.py
mgkegg/__main__.py
mgkegg/downloads.py
mgkegg/highlight.py
mgkegg/html_parser.py
mgkegg/rest.py
mgkegg/update.py
mgkegg-1.1.dist-info/LICENSE
mgkegg-1.1.dist-info/METADATA
mgkegg-1.1.dist-info/WHEEL
mgkegg-1.1.dist-info/entry_points.txt
mgkegg-1.1.dist-info/top_level.txt
mgkegg-1.1.dist-info/RECORD
