Metadata-Version: 2.1
Name: mgkegg
Version: 1.1
Summary: kegg color pathway object for metagenome
Home-page: https://github.com/QIngyuanfl/mgkegg
Author: Qingyuan Zhang
Author-email: qymyc04@live.com
License: UNKNOWN
Project-URL: Bug Tracker, https://github.com/QIngyuanfl/mgkegg/issues
Platform: UNKNOWN
Classifier: Programming Language :: Python :: 3
Classifier: License :: OSI Approved :: MIT License
Classifier: Operating System :: OS Independent
Requires-Python: >=3.7
License-File: LICENSE
Requires-Dist: aiohttp
Requires-Dist: Pillow
Requires-Dist: requests
